health_checker-0.2.0.dist-info/METADATA
health_checker-0.2.0.dist-info/RECORD
health_checker-0.2.0.dist-info/WHEEL
health_checker-0.2.0.dist-info/top_level.txt
healthchecker/__init__.py
healthchecker/async_checker.py
healthchecker/checker.py
