Metadata-Version: 2.1
Name: health-checker
Version: 0.2.0
Summary: Check if several checks pass or not
Home-page: https://bitbucket.org/sievetech/health-checker
Author: UNKNOWN
Author-email: UNKNOWN
License: UNKNOWN
Platform: UNKNOWN
